commontools/web.py
commontoolstomz/web.py
commontoolstomz-1.0.0.dist-info/METADATA
commontoolstomz-1.0.0.dist-info/WHEEL
commontoolstomz-1.0.0.dist-info/top_level.txt
commontoolstomz-1.0.0.dist-info/RECORD
