Metadata-Version: 2.1
Name: commontoolstomz
Version: 1.0.0
Summary: commontoolstomz
Author: tomzmagic
Author-email: pi_sender@163.com
Requires-Dist: requests
